spatiotemporal/__init__.py
spatiotemporal/_version.py
spatiotemporal/extras.py
spatiotemporal/models.py
spatiotemporal/stats.py
spatiotemporal/surrogates.py
spatiotemporal/tools.py
spatiotemporal-1.0.1.dist-info/METADATA
spatiotemporal-1.0.1.dist-info/WHEEL
spatiotemporal-1.0.1.dist-info/top_level.txt
spatiotemporal-1.0.1.dist-info/RECORD
