Metadata-Version: 2.1
Name: spatiotemporal
Version: 1.0.1
Summary: Tools for spatial and temporal autocorrelation
Home-page: https://github.com/mwshinn/spatiotemporal
Author: Max Shinn
Author-email: m.shinn@ucl.ac.uk
Maintainer: Max Shinn
Maintainer-email: m.shinn@ucl.ac.uk
License: MIT
Platform: UNKNOWN
Classifier: Development Status :: 4 - Beta
Classifier: Intended Audience :: Science/Research
Classifier: License :: OSI Approved :: MIT License
Classifier: Programming Language :: Python :: 3
Classifier: Topic :: Scientific/Engineering
Classifier: Topic :: Scientific/Engineering :: Physics
Classifier: Topic :: Scientific/Engineering :: Mathematics
Classifier: Topic :: Scientific/Engineering :: Medical Science Apps.
Classifier: Topic :: Scientific/Engineering :: Bio-Informatics
Requires-Python: >=3.6
Requires-Dist: numpy
Requires-Dist: scipy
Requires-Dist: pandas
